dubeolsik_automata/__init__.py
dubeolsik_automata/dubeolsik_automata.py
dubeolsik_automata-0.1.0.dist-info/LICENSE.txt
dubeolsik_automata-0.1.0.dist-info/METADATA
dubeolsik_automata-0.1.0.dist-info/WHEEL
dubeolsik_automata-0.1.0.dist-info/top_level.txt
dubeolsik_automata-0.1.0.dist-info/RECORD
