Metadata-Version: 2.1
Name: dubeolsik-automata
Version: 0.1.0
Summary: Dubeolsik automata
Home-page: https://github.com/kjh618/dubeolsik-automata
Author: Jihoon Kim, Seongyeop Yi
Author-email: kimjihoon6188@daum.net
License: UNKNOWN
Platform: UNKNOWN
Classifier: Programming Language :: Python :: 3
Classifier: Operating System :: OS Independent
Requires-Python: >=3.6
